ease_plugin/__init__.py
ease_plugin/_config_table.py
ease_plugin/plugin.py
ease_plugin-1.0.5.dist-info/METADATA
ease_plugin-1.0.5.dist-info/WHEEL
ease_plugin-1.0.5.dist-info/top_level.txt
ease_plugin-1.0.5.dist-info/RECORD
